[{"id":49,"sentiment_fake":0.1369444444,"state":"UT","rank":1},{"id":15,"sentiment_fake":0.1322222222,"state":"HI","rank":2},{"id":2,"sentiment_fake":0.1233333333,"state":"AK","rank":3},{"id":40,"sentiment_fake":0.0977777778,"state":"OK","rank":4},{"id":29,"sentiment_fake":0.093132154,"state":"MO","rank":5},{"id":56,"sentiment_fake":0.0853061224,"state":"WY","rank":6},{"id":32,"sentiment_fake":0.08390625,"state":"NV","rank":7},{"id":18,"sentiment_fake":0.0667283951,"state":"IN","rank":8},{"id":22,"sentiment_fake":0.0636734694,"state":"LA","rank":9},{"id":41,"sentiment_fake":0.0587257618,"state":"OR","rank":10},{"id":10,"sentiment_fake":0.0577777778,"state":"DE","rank":11},{"id":45,"sentiment_fake":0.0525,"state":"SC","rank":12},{"id":24,"sentiment_fake":0.0524007561,"state":"MD","rank":13},{"id":13,"sentiment_fake":0.0515345337,"state":"GA","rank":14},{"id":19,"sentiment_fake":0.0434567901,"state":"IA","rank":15},{"id":11,"sentiment_fake":0.0418959063,"state":"DC","rank":16},{"id":17,"sentiment_fake":0.0408410494,"state":"IL","rank":17},{"id":9,"sentiment_fake":0.0398765432,"state":"CT","rank":18},{"id":36,"sentiment_fake":0.039361953,"state":"NY","rank":19},{"id":26,"sentiment_fake":0.0392244898,"state":"MI","rank":20},{"id":21,"sentiment_fake":0.0367346939,"state":"KY","rank":21},{"id":4,"sentiment_fake":0.0347222222,"state":"AZ","rank":22},{"id":34,"sentiment_fake":0.0330276817,"state":"NJ","rank":23},{"id":53,"sentiment_fake":0.0321323529,"state":"WA","rank":24},{"id":12,"sentiment_fake":0.0314926632,"state":"FL","rank":25},{"id":27,"sentiment_fake":0.0297,"state":"MN","rank":26},{"id":39,"sentiment_fake":0.0271280992,"state":"OH","rank":27},{"id":35,"sentiment_fake":0.0208163265,"state":"NM","rank":28},{"id":1,"sentiment_fake":0.0186390533,"state":"AL","rank":29},{"id":48,"sentiment_fake":0.0143412305,"state":"TX","rank":30},{"id":38,"sentiment_fake":0.01,"state":"ND","rank":31},{"id":46,"sentiment_fake":0.01,"state":"SD","rank":32},{"id":5,"sentiment_fake":0.0096,"state":"AR","rank":33},{"id":6,"sentiment_fake":0.0082463877,"state":"CA","rank":34},{"id":30,"sentiment_fake":0.00765625,"state":"MT","rank":35},{"id":51,"sentiment_fake":0.0049666667,"state":"VA","rank":36},{"id":37,"sentiment_fake":0.0041838134,"state":"NC","rank":37},{"id":47,"sentiment_fake":0.0034023669,"state":"TN","rank":38},{"id":20,"sentiment_fake":0.0019282451,"state":"KS","rank":39},{"id":8,"sentiment_fake":0.0014984391,"state":"CO","rank":40},{"id":44,"sentiment_fake":-3.108624469e-18,"state":"RI","rank":41},{"id":42,"sentiment_fake":-0.0022119342,"state":"PA","rank":42},{"id":23,"sentiment_fake":-0.0081632653,"state":"ME","rank":43},{"id":55,"sentiment_fake":-0.0090277778,"state":"WI","rank":44},{"id":54,"sentiment_fake":-0.01,"state":"WV","rank":45},{"id":16,"sentiment_fake":-0.0288888889,"state":"ID","rank":46},{"id":25,"sentiment_fake":-0.0290589569,"state":"MA","rank":47},{"id":28,"sentiment_fake":-0.0355555556,"state":"MS","rank":48},{"id":33,"sentiment_fake":-0.0375,"state":"NH","rank":49},{"id":31,"sentiment_fake":-0.06,"state":"NE","rank":50},{"id":50,"sentiment_fake":-0.1072,"state":"VT","rank":51},{"id":72,"sentiment_fake":0.0,"state":"PR","rank":52},{"id":78,"sentiment_fake":0,"state":"","rank":0}]